CHANGES.rst
LICENSE.rst
MANIFEST.in
README.rst
setup.py
collective/__init__.py
collective.fullview.egg-info/PKG-INFO
collective.fullview.egg-info/SOURCES.txt
collective.fullview.egg-info/dependency_links.txt
collective.fullview.egg-info/entry_points.txt
collective.fullview.egg-info/namespace_packages.txt
collective.fullview.egg-info/not-zip-safe
collective.fullview.egg-info/requires.txt
collective.fullview.egg-info/top_level.txt
collective/fullview/__init__.py
collective/fullview/configure.zcml
collective/fullview/full_view.pt
collective/fullview/full_view.py
collective/fullview/full_view_item.pt
collective/fullview/locales/merge_plone.pot
collective/fullview/locales/plone.pot
collective/fullview/locales/de/LC_MESSAGES/plone.po
collective/fullview/locales/en/LC_MESSAGES/plone.po
collective/fullview/profiles/default/metadata.xml
collective/fullview/profiles/default/types.xml
collective/fullview/profiles/default/types/Collection.xml
collective/fullview/profiles/default/types/Folder.xml
collective/fullview/profiles/default/types/Plone_Site.xml
collective/fullview/profiles/default/types/Topic.xml