Metadata-Version: 1.1
Name: collective.fullview
Version: 1.3
Summary: Alternative full view for Plone with support for BrowserViews.
Home-page: http://github.com/collective/collective.fullview
Author: Johannes Raggam
Author-email: raggam-nl@adm.at
License: GPL
Keywords: plone view
Platform: UNKNOWN
Classifier: Framework :: Plone
Classifier: Programming Language :: Python
